README.rst
setup.cfg
setup.py
discogs_cli/__init__.py
discogs_cli/completions.py
discogs_cli/discogs.py
discogs_cli/main.py
discogs_cli/main_cli.py
discogs_cli/pyglexer.py
discogs_cli.egg-info/PKG-INFO
discogs_cli.egg-info/SOURCES.txt
discogs_cli.egg-info/dependency_links.txt
discogs_cli.egg-info/entry_points.txt
discogs_cli.egg-info/requires.txt
discogs_cli.egg-info/top_level.txt
discogs_cli/ext/__init__.py
discogs_cli/ext/completer.py
discogs_cli/ext/utils.py