Metadata-Version: 1.0
Name: discogs-cli
Version: 1.1.0
Summary: View and search for artists, labels and releases in the Discogs.com library, from the command line.
Home-page: https://github.com/jesseward/discogs-cli
Author: Jesse Ward
Author-email: jesse@jesseward.com
License: MIT
Platform: UNKNOWN
Classifier: Environment :: Console
Classifier: Development Status :: 5 - Production/Stable
Classifier: Programming Language :: Python :: 2.6
Classifier: Programming Language :: Python :: 2.7
Classifier: License :: OSI Approved :: MIT License
Classifier: Operating System :: OS Independent
